SAP_Data_CE_PC_Daily/__init__.py
SAP_Data_CE_PC_Daily/main.py
SAP_Data_CE_PC_Daily-0.0.2.dist-info/LICENSE
SAP_Data_CE_PC_Daily-0.0.2.dist-info/METADATA
SAP_Data_CE_PC_Daily-0.0.2.dist-info/WHEEL
SAP_Data_CE_PC_Daily-0.0.2.dist-info/top_level.txt
SAP_Data_CE_PC_Daily-0.0.2.dist-info/RECORD
