Metadata-Version: 2.1
Name: SAP-Data-CE-PC-Daily
Version: 0.0.2
Summary: A Python package to fetch and print Dataframe for SAP Data CE PC Daily.
Author-email: Hossam Ibrahim <hossam.ibrahim@hlag.com>
License: Copyright (c) [2023] [Hossam_Ibrahim]
License-File: LICENSE
Requires-Dist: requests
Requires-Dist: pandas
